reproscreener/02_manual_eval_explorer.py
reproscreener/__init__.py
reproscreener/keywords.py
reproscreener/main.py
reproscreener/paper_analyzer.py
reproscreener/repo_analyzer.py
reproscreener/webui.py
reproscreener/deprecated/gdrive_downloader.py
reproscreener/deprecated/gold_standard.py
reproscreener/deprecated/keywords.py
reproscreener/deprecated/main.py
reproscreener/deprecated/repo_eval.py
reproscreener/deprecated/report.py
reproscreener/deprecated/scrape_arxiv.py
reproscreener/deprecated/tex_eval.py
reproscreener/deprecated/utils.py
reproscreener/deprecated/webui.py
reproscreener/deprecated/llm/prompt.txt
reproscreener/deprecated/llm/prompts.py
reproscreener/deprecated/llm/scibert.py
reproscreener/deprecated/llm/spectre.py
reproscreener/deprecated/plots/gold_standard_heatmaps.py
reproscreener/deprecated/plots/repo_eval_heatmaps.py
reproscreener/deprecated/plots/tex_eval_heatmaps.py
reproscreener/manual_evaluations/__init__.py
reproscreener/manual_evaluations/abstract_gpt_agreement_with_manual.csv
reproscreener/manual_evaluations/abstract_manual_evaluation.csv
reproscreener/manual_evaluations/full_manuscript_manual_evaluation.csv
reproscreener/manual_evaluations/manual_eval.py
reproscreener/manual_evaluations/manual_eval_viewer.py
reproscreener/metrics/gunderson-2018/main.md
reproscreener/metrics/gunderson-2018/notes.md
reproscreener/metrics/gunderson-2018-revised/main-codebook.json
reproscreener/metrics/gunderson-2018-revised/main.json
reproscreener/metrics/gunderson-2018-revised/main.md
reproscreener/metrics/raghupathi-2022/main.md
reproscreener-2.0.0.dist-info/METADATA
reproscreener-2.0.0.dist-info/WHEEL
reproscreener-2.0.0.dist-info/entry_points.txt
reproscreener-2.0.0.dist-info/licenses/LICENSE
reproscreener-2.0.0.dist-info/RECORD
