Metadata-Version: 2.4
Name: reproscreener
Version: 2.0.0
Summary: Automated reproducibility evaluation of research
Author-email: Adhithya Bhaskar <adhithyabhaskar@gmail.com>
License-File: LICENSE
Requires-Python: >=3.13
Requires-Dist: docling>=2.32.0
Requires-Dist: exrex>=0.12.0
Requires-Dist: feedparser>=6.0.11
Requires-Dist: flashtext>=2.7
Requires-Dist: gitpython>=3.1.44
Requires-Dist: marimo>=0.13.15
Requires-Dist: mkdocs-bibtex>=4.2.5
Requires-Dist: mkdocs-jupyter>=0.25.1
Requires-Dist: mkdocs-macros-plugin>=1.3.7
Requires-Dist: mkdocs-marimo>=0.2.1
Requires-Dist: mkdocs-material>=9.6.14
Requires-Dist: mkdocs>=1.6.1
Requires-Dist: mkdocstrings-python>=1.16.12
Requires-Dist: notebook>=7.4.2
Requires-Dist: pandas>=2.2.3
Requires-Dist: pathlib>=1.0.1
Requires-Dist: plotly>=6.1.1
Requires-Dist: pymdown-extensions>=10.15
Requires-Dist: requests>=2.32.3
Requires-Dist: rich>=14.0.0
Requires-Dist: scikit-learn>=1.6.1
Requires-Dist: seaborn>=0.13.2
Requires-Dist: streamlit>=1.45.1
Requires-Dist: urlextract>=1.9.0
Requires-Dist: watchdog>=6.0.0
